{
	"info": {
		"_postman_id": "a1b2c3d4-e5f6-4a7b-8c9d-1e2f3a4b5c6d",
		"name": "KPA Local API",
		"schema": "https://schema.getpostman.com/json/collection/v2.1.0/collection.json",
		"_exporter_id": "30281483"
	},
	"item": [
		{
			"name": "Create Wheel Specification",
			"request": {
				"method": "POST",
				"header": [],
				"body": {
					"mode": "raw",
					"raw": "{\r\n  \"formNumber\": \"WHEEL-TEST-001\",\r\n  \"submittedBy\": \"kunal_singh\",\r\n  \"submittedDate\": \"2025-07-20\",\r\n  \"fields\": {\r\n    \"treadDiameterNew\": \"915 (900-1000)\",\r\n    \"lastShopIssueSize\": \"837 (800-900)\",\r\n    \"condemningDia\": \"825 (800-900)\",\r\n    \"wheelGauge\": \"1600 (+2,-1)\",\r\n    \"variationSameAxle\": \"0.5\",\r\n    \"variationSameBogie\": \"5\",\r\n    \"variationSameCoach\": \"13\",\r\n    \"wheelProfile\": \"29.4 Flange Thickness\",\r\n    \"intermediateWWP\": \"20 TO 28\",\r\n    \"bearingSeatDiameter\": \"130.043 TO 130.068\",\r\n    \"rollerBearingOuterDia\": \"280 (+0.0/-0.035)\",\r\n    \"rollerBearingBoreDia\": \"130 (+0.0/-0.025)\",\r\n    \"rollerBearingWidth\": \"93 (+0/-0.250)\",\r\n    \"axleBoxHousingBoreDia\": \"280 (+0.030/+0.052)\",\r\n    \"wheelDiscWidth\": \"127 (+4/-0)\"\r\n  }\r\n}",
					"options": {
						"raw": {
							"language": "json"
						}
					}
				},
				"url": {
					"raw": "http://127.0.0.1:8000/api/forms/wheel-specifications",
					"protocol": "http",
					"host": [
						"127",
						"0",
						"0",
						"1"
					],
					"port": "8000",
					"path": [
						"api",
						"forms",
						"wheel-specifications"
					]
				}
			},
			"response": []
		},
		{
			"name": "Get All Wheel Specifications",
			"request": {
				"method": "GET",
				"header": [],
				"url": {
					"raw": "http://127.0.0.1:8000/api/forms/wheel-specifications",
					"protocol": "http",
					"host": [
						"127",
						"0",
						"0",
						"1"
					],
					"port": "8000",
					"path": [
						"api",
						"forms",
						"wheel-specifications"
					]
				}
			},
			"response": []
		}
	]
}
